simpcalc/__init__.py
simpcalc/errors.py
simpcalc/simpcalc.py
simpcalci-0.0.2.dist-info/LICENSE
simpcalci-0.0.2.dist-info/METADATA
simpcalci-0.0.2.dist-info/WHEEL
simpcalci-0.0.2.dist-info/top_level.txt
simpcalci-0.0.2.dist-info/RECORD
